poetry_plugin_generate_setup/__init__.py
poetry_plugin_generate_setup/plugin.py
poetry_plugin_generate_setup-0.1.0.dist-info/METADATA
poetry_plugin_generate_setup-0.1.0.dist-info/WHEEL
poetry_plugin_generate_setup-0.1.0.dist-info/entry_points.txt
poetry_plugin_generate_setup-0.1.0.dist-info/RECORD
