Metadata-Version: 2.1
Name: poetry-plugin-generate-setup
Version: 0.1.0
Summary: 
Author: Oleg Semenovsky
Requires-Python: >=3.11,<4.0
Classifier: Programming Language :: Python :: 3
Classifier: Programming Language :: Python :: 3.11
Classifier: Programming Language :: Python :: 3.12
Requires-Dist: poetry (>=1.7.1,<2.0.0)
